{
    "br": [
        23,
        12,
        17,
        5,
        12,
        13,
        5,
        10,
        17,
        11,
        15,
        23,
        10,
        22,
        9,
        7,
        12,
        7,
        22,
        11,
        5,
        23,
        10,
        18,
        9,
        24,
        9,
        24,
        23,
        23,
        9,
        12,
        24
    ],
    "sr": [
        6,
        6,
        9,
        0,
        4,
        0,
        8,
        3,
        3,
        0,
        7,
        6,
        6,
        3,
        3,
        9,
        10,
        1,
        6,
        0,
        3,
        9,
        9,
        5,
        6,
        5,
        6,
        9,
        10,
        4,
        1,
        4,
        8
    ],
    "imbalance_force": [
        1260.28,
        830.04,
        2265.19
    ],
    "wob": [
        25000.03,
        15000.06,
        35000.67
    ],
    "torque": [
        4493.07,
        2646.12,
        6344.01
    ],
    "rop": [
        143.08,
        127.39,
        115.22
    ],
    "rpm": [
        240.0,
        240.0,
        200.0
    ],
    "fn": [
        [
            2475.6,
            1554.2,
            1881.8,
            1296.6,
            1525.8,
            1431.7,
            911.2,
            1208.2,
            1214.9,
            1114.3,
            1166.1,
            1449.6,
            1023.4,
            1363.6,
            931.8,
            893.9,
            933.7,
            805.9,
            1103.5,
            760.5,
            622.8,
            867.7,
            585.7,
            653.7,
            413.9,
            542.9,
            89.1,
            0.1,
            0.1,
            0.7,
            0.1,
            0.0,
            0.0
        ],
        [
            1663.1,
            940.7,
            1179.8,
            721.2,
            916.8,
            852.0,
            494.3,
            698.4,
            746.1,
            640.7,
            713.3,
            972.7,
            583.2,
            900.8,
            513.3,
            484.9,
            548.6,
            423.8,
            733.6,
            422.2,
            301.7,
            577.8,
            314.3,
            411.2,
            209.2,
            330.6,
            36.7,
            0.1,
            0.1,
            0.5,
            0.0,
            0.0,
            0.0
        ],
        [
            4364.5,
            2627.2,
            3326.2,
            2164.5,
            2629.3,
            2299.9,
            1207.5,
            1707.3,
            1613.3,
            1409.5,
            1423.1,
            2197.1,
            1213.3,
            1914.9,
            1043.4,
            995.9,
            1044.3,
            827.7,
            1317.5,
            710.0,
            506.8,
            891.6,
            448.0,
            491.9,
            279.9,
            441.5,
            46.7,
            0.1,
            0.1,
            0.5,
            0.0,
            0.0,
            0.0
        ]
    ],
    "workrate_fn": [
        [
            1243.8,
            1767.8,
            3210.9,
            2949.9,
            4302.5,
            4778.0,
            3423.8,
            5001.6,
            5500.7,
            5461.0,
            6122.2,
            8124.2,
            6087.5,
            8583.0,
            6165.4,
            6187.5,
            6724.9,
            6024.2,
            8539.8,
            6068.5,
            5099.2,
            7265.6,
            5004.0,
            5677.0,
            3641.4,
            4819.0,
            793.1,
            1.2,
            1.2,
            6.4,
            0.5,
            0.2,
            0.0
        ],
        [
            844.8,
            1077.2,
            2023.0,
            1644.8,
            2591.8,
            2849.6,
            1861.7,
            2900.3,
            3388.7,
            3147.0,
            3754.2,
            5462.2,
            3474.8,
            5677.7,
            3400.9,
            3360.2,
            3955.7,
            3170.9,
            5681.8,
            3371.8,
            2471.6,
            4840.2,
            2686.7,
            3572.6,
            1841.3,
            2935.0,
            326.6,
            0.8,
            0.9,
            4.0,
            0.2,
            0.1,
            0.0
        ],
        [
            1833.6,
            2495.2,
            4736.5,
            4106.8,
            6182.8,
            6400.5,
            3783.7,
            5895.1,
            6092.8,
            5760.0,
            6230.7,
            10266.9,
            6017.1,
            10048.2,
            5755.7,
            5746.8,
            6269.7,
            5157.2,
            8498.4,
            4722.3,
            3458.2,
            6222.4,
            3189.8,
            3560.3,
            2052.2,
            3265.9,
            346.4,
            0.5,
            0.8,
            3.6,
            0.2,
            0.1,
            0.0
        ]
    ]
}