{
    "br": [
        21,
        22,
        11,
        17,
        7,
        21,
        21,
        8,
        21,
        17,
        10,
        15,
        20,
        10,
        20,
        21,
        8,
        13,
        25,
        8,
        18,
        25,
        14,
        14,
        20,
        9,
        20,
        18,
        16,
        18,
        24,
        12,
        22
    ],
    "sr": [
        1,
        1,
        0,
        6,
        2,
        7,
        3,
        7,
        6,
        2,
        5,
        10,
        8,
        3,
        4,
        7,
        4,
        9,
        0,
        9,
        3,
        0,
        7,
        9,
        10,
        4,
        1,
        0,
        5,
        0,
        9,
        0,
        5
    ],
    "imbalance_force": [
        1048.37,
        555.3,
        1863.06
    ],
    "wob": [
        25000.03,
        15000.25,
        35001.75
    ],
    "torque": [
        4451.96,
        2608.62,
        6257.19
    ],
    "rop": [
        134.43,
        115.18,
        109.92
    ],
    "rpm": [
        240.0,
        240.0,
        200.0
    ],
    "fn": [
        [
            2042.7,
            1855.0,
            1501.0,
            1656.4,
            1285.4,
            1647.3,
            1209.9,
            1114.7,
            1274.3,
            1224.9,
            1009.1,
            1125.1,
            1239.6,
            987.8,
            1087.6,
            1132.1,
            800.4,
            883.4,
            1124.8,
            701.4,
            733.2,
            862.5,
            587.4,
            561.2,
            529.1,
            315.6,
            105.8,
            0.0,
            0.0,
            0.1,
            0.0,
            0.4,
            0.0
        ],
        [
            1275.3,
            1190.8,
            854.8,
            1011.7,
            705.4,
            1039.3,
            782.3,
            609.9,
            797.9,
            745.8,
            550.8,
            674.3,
            793.5,
            534.0,
            693.5,
            734.6,
            415.6,
            510.4,
            739.1,
            360.1,
            452.0,
            560.7,
            334.7,
            313.8,
            317.3,
            145.4,
            52.5,
            0.0,
            0.0,
            0.0,
            0.0,
            0.2,
            0.0
        ],
        [
            3315.2,
            3394.2,
            2477.5,
            2848.1,
            2102.1,
            2825.3,
            1829.8,
            1516.5,
            1791.7,
            1631.6,
            1181.7,
            1401.5,
            1660.3,
            1149.5,
            1295.4,
            1452.9,
            834.2,
            959.0,
            1434.8,
            627.9,
            609.6,
            932.5,
            463.5,
            430.6,
            371.4,
            194.7,
            49.9,
            0.0,
            0.0,
            0.0,
            0.0,
            0.2,
            0.0
        ]
    ],
    "workrate_fn": [
        [
            1062.3,
            2115.9,
            2565.2,
            3773.9,
            3626.9,
            5497.7,
            4546.8,
            4622.7,
            5774.2,
            6007.7,
            5309.8,
            6314.1,
            7380.9,
            6221.2,
            7195.3,
            7838.3,
            5767.7,
            6607.7,
            8706.3,
            5599.4,
            6002.9,
            7222.2,
            5020.3,
            4875.3,
            4656.4,
            2801.9,
            941.8,
            0.0,
            0.3,
            0.7,
            0.0,
            3.6,
            0.0
        ],
        [
            675.5,
            1370.0,
            1469.8,
            2312.3,
            1997.0,
            3478.3,
            2949.1,
            2539.6,
            3629.9,
            3669.2,
            2907.9,
            3793.9,
            4735.7,
            3369.4,
            4596.2,
            5094.2,
            2999.2,
            3822.8,
            5728.1,
            2877.4,
            3704.3,
            4699.5,
            2862.6,
            2727.3,
            2793.2,
            1291.5,
            467.3,
            0.1,
            0.1,
            0.4,
            0.3,
            2.1,
            0.0
        ],
        [
            1440.0,
            3230.1,
            3531.1,
            5409.6,
            4945.2,
            7860.7,
            5732.6,
            5243.7,
            6769.5,
            6671.5,
            5183.6,
            6556.4,
            8240.6,
            6034.6,
            7143.2,
            8384.0,
            5010.3,
            5978.6,
            9256.7,
            4177.5,
            4159.3,
            6507.5,
            3301.2,
            3117.4,
            2723.8,
            1440.6,
            370.1,
            0.0,
            0.1,
            0.3,
            0.0,
            1.7,
            0.0
        ]
    ]
}