{
    "br": [
        19,
        25,
        17,
        20,
        5,
        17,
        22,
        18,
        8,
        12,
        12,
        15,
        10,
        12,
        16,
        13,
        22,
        11,
        19,
        6,
        12,
        5,
        23,
        8,
        16,
        10,
        8,
        9,
        13,
        13,
        20,
        11,
        19
    ],
    "sr": [
        7,
        5,
        4,
        4,
        5,
        8,
        4,
        4,
        8,
        2,
        1,
        2,
        8,
        0,
        0,
        7,
        9,
        0,
        8,
        0,
        6,
        6,
        8,
        7,
        8,
        9,
        7,
        10,
        2,
        6,
        6,
        10,
        2
    ],
    "imbalance_force": [
        1243.89,
        919.54,
        1990.62
    ],
    "wob": [
        25000.38,
        15000.04,
        34998.88
    ],
    "torque": [
        4375.97,
        2553.78,
        6135.88
    ],
    "rop": [
        137.5,
        119.72,
        111.34
    ],
    "rpm": [
        240.0,
        240.0,
        200.0
    ],
    "fn": [
        [
            2195.0,
            2067.6,
            1762.9,
            1801.0,
            1258.0,
            1525.9,
            1255.2,
            1406.0,
            990.0,
            1120.1,
            1052.3,
            1125.1,
            1016.1,
            1038.8,
            1017.1,
            952.9,
            1123.7,
            843.7,
            986.9,
            676.6,
            695.4,
            593.2,
            765.7,
            518.1,
            474.9,
            333.4,
            84.0,
            0.0,
            0.5,
            0.0,
            0.1,
            0.0,
            0.1
        ],
        [
            1420.1,
            1380.8,
            1080.9,
            1138.5,
            687.0,
            937.1,
            827.6,
            879.8,
            529.8,
            646.3,
            593.7,
            666.5,
            570.8,
            585.3,
            610.5,
            555.9,
            741.3,
            468.2,
            631.0,
            328.8,
            390.9,
            274.8,
            498.6,
            252.6,
            274.1,
            161.8,
            32.7,
            0.0,
            0.3,
            0.0,
            0.1,
            0.0,
            0.1
        ],
        [
            3552.2,
            3981.5,
            3016.1,
            3202.9,
            2057.8,
            2466.4,
            1924.9,
            2103.2,
            1204.1,
            1433.2,
            1242.9,
            1417.3,
            1207.0,
            1233.4,
            1174.2,
            1081.3,
            1450.9,
            889.1,
            1026.4,
            594.6,
            593.9,
            443.9,
            747.9,
            374.7,
            328.0,
            204.7,
            44.9,
            0.0,
            0.3,
            0.0,
            0.1,
            0.0,
            0.1
        ]
    ],
    "workrate_fn": [
        [
            1103.6,
            2344.8,
            3006.0,
            4099.6,
            3550.9,
            5091.9,
            4710.9,
            5826.5,
            4491.3,
            5493.8,
            5532.5,
            6312.7,
            6050.9,
            6542.3,
            6730.1,
            6594.2,
            8094.2,
            6309.6,
            7642.3,
            5400.5,
            5696.3,
            4969.2,
            6543.8,
            4500.4,
            4178.7,
            2960.1,
            747.7,
            0.1,
            4.6,
            0.2,
            1.0,
            0.4,
            1.1
        ],
        [
            723.4,
            1578.6,
            1853.4,
            2599.3,
            1944.8,
            3134.9,
            3115.1,
            3659.8,
            2411.7,
            3178.2,
            3131.1,
            3748.5,
            3406.3,
            3692.1,
            4046.3,
            3852.5,
            5346.3,
            3505.1,
            4890.4,
            2626.5,
            3204.0,
            2304.0,
            4263.9,
            2195.3,
            2412.8,
            1436.7,
            290.9,
            0.1,
            2.5,
            0.2,
            0.8,
            0.2,
            0.7
        ],
        [
            1492.5,
            3769.3,
            4290.8,
            6079.4,
            4843.2,
            6862.2,
            6024.0,
            7268.7,
            4555.8,
            5860.8,
            5448.8,
            6629.9,
            5992.5,
            6475.3,
            6476.7,
            6237.3,
            8711.4,
            5542.5,
            6624.1,
            3955.8,
            4054.5,
            3099.1,
            5327.2,
            2712.3,
            2405.1,
            1514.4,
            333.1,
            0.1,
            2.1,
            0.1,
            0.4,
            0.2,
            0.5
        ]
    ]
}