{
    "br": [
        24,
        23,
        5,
        15,
        23,
        19,
        22,
        6,
        17,
        17,
        10,
        17,
        23,
        23,
        21,
        18,
        14,
        25,
        24,
        23,
        18,
        7,
        22,
        15,
        11,
        20,
        11,
        20,
        22,
        6,
        22,
        18,
        18
    ],
    "sr": [
        8,
        1,
        2,
        3,
        3,
        2,
        8,
        1,
        1,
        6,
        3,
        6,
        1,
        0,
        9,
        3,
        4,
        10,
        4,
        9,
        10,
        0,
        3,
        10,
        9,
        3,
        5,
        2,
        0,
        9,
        8,
        7,
        1
    ],
    "imbalance_force": [
        2052.89,
        1362.38,
        3768.81
    ],
    "wob": [
        24999.06,
        14999.76,
        35000.23
    ],
    "torque": [
        4419.39,
        2569.99,
        6158.02
    ],
    "rop": [
        126.57,
        105.03,
        103.57
    ],
    "rpm": [
        240.0,
        240.0,
        200.0
    ],
    "fn": [
        [
            2375.3,
            1835.1,
            1268.9,
            1489.1,
            1800.3,
            1454.6,
            1216.7,
            1012.0,
            1065.8,
            1189.7,
            950.0,
            1096.0,
            1232.0,
            1241.2,
            1110.0,
            976.8,
            837.5,
            1140.5,
            1039.4,
            909.9,
            725.2,
            565.0,
            687.9,
            555.9,
            389.9,
            395.8,
            70.6,
            0.1,
            0.1,
            0.0,
            0.2,
            0.1,
            0.1
        ],
        [
            1561.8,
            1163.6,
            647.0,
            864.9,
            1141.7,
            876.7,
            778.8,
            512.6,
            614.3,
            715.0,
            500.0,
            651.7,
            782.8,
            783.1,
            700.4,
            594.6,
            469.2,
            746.2,
            660.9,
            575.3,
            441.7,
            260.3,
            430.2,
            303.1,
            195.7,
            225.4,
            29.9,
            0.1,
            0.1,
            0.0,
            0.2,
            0.1,
            0.1
        ],
        [
            4149.8,
            3309.8,
            1940.8,
            2400.7,
            3256.2,
            2295.2,
            1868.9,
            1332.6,
            1327.8,
            1541.0,
            1073.9,
            1339.6,
            1678.4,
            1672.0,
            1402.5,
            1097.8,
            862.4,
            1560.5,
            1237.5,
            981.2,
            592.1,
            426.6,
            608.2,
            417.3,
            266.9,
            219.7,
            38.6,
            0.0,
            0.1,
            0.0,
            0.2,
            0.1,
            0.1
        ]
    ],
    "workrate_fn": [
        [
            1211.1,
            2099.6,
            2176.0,
            3390.5,
            5082.2,
            4861.1,
            4578.8,
            4204.6,
            4839.7,
            5842.1,
            5004.2,
            6153.7,
            7335.5,
            7818.6,
            7351.7,
            6766.3,
            6033.6,
            8531.8,
            8046.6,
            7262.7,
            5942.3,
            4734.6,
            5879.6,
            4830.9,
            3432.0,
            3513.8,
            628.8,
            0.9,
            0.8,
            0.1,
            2.1,
            1.0,
            1.2
        ],
        [
            810.4,
            1343.4,
            1116.7,
            1976.5,
            3235.8,
            2939.5,
            2941.5,
            2139.5,
            2801.8,
            3523.8,
            2644.6,
            3670.6,
            4675.3,
            4944.3,
            4648.9,
            4127.2,
            3386.9,
            5590.5,
            5123.8,
            4598.0,
            3623.8,
            2183.8,
            3680.2,
            2635.7,
            1722.6,
            2001.4,
            266.4,
            0.5,
            0.5,
            0.1,
            1.5,
            0.7,
            0.6
        ],
        [
            1766.1,
            3159.0,
            2775.6,
            4556.5,
            7663.4,
            6394.2,
            5863.6,
            4616.1,
            5026.8,
            6308.5,
            4715.8,
            6270.2,
            8330.3,
            8779.1,
            7742.3,
            6338.6,
            5178.5,
            9729.4,
            7984.9,
            6527.2,
            4043.4,
            2979.8,
            4332.5,
            3022.4,
            1957.7,
            1625.3,
            286.0,
            0.4,
            0.4,
            0.0,
            1.1,
            0.4,
            0.5
        ]
    ]
}