{
    "br": [
        16,
        13,
        20,
        8,
        5,
        15,
        10,
        22,
        22,
        9,
        15,
        15,
        5,
        18,
        18,
        18,
        23,
        11,
        14,
        10,
        6,
        18,
        17,
        19,
        19,
        23,
        22,
        12,
        20,
        8,
        20,
        8,
        10
    ],
    "sr": [
        2,
        1,
        10,
        3,
        1,
        10,
        4,
        7,
        4,
        7,
        2,
        2,
        3,
        0,
        9,
        7,
        3,
        2,
        0,
        0,
        7,
        8,
        0,
        3,
        0,
        2,
        0,
        6,
        4,
        5,
        9,
        0,
        10
    ],
    "imbalance_force": [
        507.36,
        213.93,
        862.49
    ],
    "wob": [
        25000.36,
        14999.98,
        34999.07
    ],
    "torque": [
        4614.32,
        2712.19,
        6477.1
    ],
    "rop": [
        142.89,
        124.83,
        115.79
    ],
    "rpm": [
        240.0,
        240.0,
        200.0
    ],
    "fn": [
        [
            1984.6,
            1546.3,
            2025.0,
            1408.2,
            1279.0,
            1532.5,
            980.9,
            1608.5,
            1390.9,
            1100.8,
            1155.8,
            1161.5,
            919.5,
            1202.0,
            1121.2,
            1072.7,
            1150.8,
            878.2,
            909.1,
            747.9,
            644.9,
            751.3,
            652.1,
            660.3,
            511.8,
            507.9,
            129.6,
            0.0,
            0.2,
            0.0,
            0.0,
            0.3,
            0.0
        ],
        [
            1200.9,
            924.4,
            1285.3,
            801.1,
            703.6,
            925.7,
            559.3,
            1055.3,
            889.2,
            620.0,
            685.2,
            691.5,
            467.1,
            743.4,
            712.2,
            682.5,
            761.8,
            491.8,
            524.7,
            401.7,
            320.5,
            471.6,
            392.3,
            413.8,
            314.0,
            304.2,
            63.7,
            0.0,
            0.1,
            0.0,
            0.0,
            0.2,
            0.0
        ],
        [
            3192.6,
            2643.7,
            3750.1,
            2397.3,
            2173.5,
            2510.9,
            1321.9,
            2615.3,
            2056.4,
            1396.6,
            1436.5,
            1506.9,
            1051.2,
            1520.8,
            1353.3,
            1285.9,
            1505.2,
            957.7,
            959.4,
            701.7,
            541.7,
            607.5,
            515.5,
            493.5,
            340.8,
            381.7,
            75.2,
            0.0,
            0.1,
            0.0,
            0.0,
            0.2,
            0.0
        ]
    ],
    "workrate_fn": [
        [
            1031.3,
            1756.4,
            3454.1,
            3205.1,
            3606.8,
            5115.4,
            3680.6,
            6648.9,
            6294.2,
            5396.7,
            6071.1,
            6513.0,
            5471.7,
            7564.7,
            7415.7,
            7420.0,
            8283.1,
            6566.9,
            7037.4,
            5968.4,
            5281.0,
            6291.9,
            5571.0,
            5734.2,
            4502.0,
            4507.9,
            1153.2,
            0.3,
            1.5,
            0.3,
            0.1,
            3.0,
            0.0
        ],
        [
            634.6,
            1057.9,
            2205.0,
            1828.4,
            1990.0,
            3097.6,
            2104.5,
            4379.2,
            4038.7,
            3046.8,
            3609.7,
            3886.0,
            2784.9,
            4685.9,
            4717.9,
            4726.8,
            5489.9,
            3681.4,
            4065.5,
            3208.1,
            2626.1,
            3951.6,
            3353.0,
            3595.5,
            2763.0,
            2700.7,
            566.6,
            0.1,
            0.9,
            0.2,
            0.1,
            1.6,
            0.0
        ],
        [
            1387.3,
            2506.4,
            5336.9,
            4549.6,
            5110.8,
            6988.0,
            4136.1,
            9016.0,
            7761.1,
            5708.5,
            6291.7,
            7044.5,
            5214.6,
            7978.3,
            7461.1,
            7414.5,
            9030.6,
            5969.4,
            6190.2,
            4667.3,
            3697.3,
            4239.9,
            3670.4,
            3571.5,
            2498.9,
            2823.4,
            557.8,
            0.1,
            0.6,
            0.2,
            0.0,
            1.4,
            0.0
        ]
    ]
}