{
    "br": [
        14,
        22,
        21,
        12,
        12,
        15,
        9,
        16,
        15,
        22,
        17,
        10,
        11,
        14,
        25,
        16,
        5,
        18,
        6,
        25,
        22,
        22,
        22,
        18,
        16,
        24,
        21,
        6,
        14,
        6,
        13,
        13,
        15
    ],
    "sr": [
        1,
        5,
        3,
        6,
        5,
        4,
        6,
        9,
        6,
        10,
        0,
        5,
        9,
        0,
        1,
        8,
        9,
        2,
        8,
        3,
        9,
        7,
        7,
        2,
        2,
        8,
        0,
        3,
        10,
        6,
        10,
        0,
        4
    ],
    "imbalance_force": [
        1393.21,
        881.24,
        2349.43
    ],
    "wob": [
        24999.65,
        15000.2,
        34999.54
    ],
    "torque": [
        4521.25,
        2664.79,
        6346.89
    ],
    "rop": [
        135.38,
        116.44,
        110.59
    ],
    "rpm": [
        240.0,
        240.0,
        200.0
    ],
    "fn": [
        [
            1795.0,
            1872.0,
            1927.0,
            1485.2,
            1467.8,
            1439.5,
            940.9,
            1343.6,
            1098.9,
            1461.2,
            1150.4,
            1016.5,
            1026.0,
            1055.7,
            1273.9,
            1018.6,
            769.9,
            967.6,
            765.7,
            987.7,
            836.4,
            790.6,
            722.1,
            615.8,
            450.3,
            513.1,
            108.8,
            0.0,
            0.1,
            0.3,
            0.0,
            0.4,
            0.0
        ],
        [
            1046.9,
            1211.7,
            1214.4,
            866.3,
            855.8,
            852.3,
            525.3,
            821.8,
            638.2,
            959.1,
            691.6,
            558.4,
            581.2,
            605.0,
            843.7,
            621.5,
            382.3,
            601.1,
            378.4,
            652.4,
            541.6,
            508.3,
            462.1,
            369.1,
            258.2,
            298.7,
            54.0,
            0.0,
            0.0,
            0.1,
            0.0,
            0.3,
            0.0
        ],
        [
            2762.2,
            3436.1,
            3488.2,
            2473.7,
            2463.7,
            2303.2,
            1253.9,
            1967.5,
            1380.1,
            2228.1,
            1427.6,
            1233.3,
            1236.1,
            1263.3,
            1809.8,
            1201.1,
            786.7,
            1079.9,
            738.0,
            1171.5,
            838.5,
            755.2,
            661.5,
            460.4,
            311.0,
            421.3,
            58.3,
            0.0,
            0.0,
            0.2,
            0.0,
            0.2,
            0.0
        ]
    ],
    "workrate_fn": [
        [
            931.5,
            2126.7,
            3288.9,
            3384.5,
            4142.6,
            4808.1,
            3537.4,
            5570.1,
            4980.3,
            7161.8,
            6049.5,
            5706.3,
            6111.6,
            6646.2,
            8425.5,
            7054.6,
            5547.5,
            7238.5,
            5928.3,
            7877.4,
            6847.1,
            6620.1,
            6170.3,
            5348.5,
            3962.4,
            4555.0,
            968.7,
            0.2,
            0.6,
            2.6,
            0.3,
            3.4,
            0.3
        ],
        [
            552.9,
            1388.1,
            2085.5,
            1980.2,
            2423.1,
            2854.4,
            1980.8,
            3420.6,
            2903.4,
            4714.5,
            3649.3,
            3142.6,
            3469.6,
            3815.7,
            5590.5,
            4311.1,
            2758.9,
            4502.4,
            2932.8,
            5207.8,
            4437.8,
            4259.3,
            3951.7,
            3207.6,
            2273.1,
            2652.0,
            480.3,
            0.1,
            0.3,
            1.2,
            0.3,
            2.2,
            0.2
        ],
        [
            1197.2,
            3256.6,
            4965.1,
            4699.8,
            5797.0,
            6413.1,
            3930.3,
            6800.6,
            5215.2,
            9104.3,
            6259.1,
            5771.3,
            6137.5,
            6629.4,
            9977.6,
            6933.2,
            4725.0,
            6733.0,
            4762.4,
            7787.0,
            5720.3,
            5270.0,
            4710.7,
            3333.0,
            2280.5,
            3116.4,
            432.4,
            0.1,
            0.4,
            1.2,
            0.2,
            1.6,
            0.2
        ]
    ]
}